easy_user_input/__init__.py
easy_user_input/easy_user_input.py
easy_user_input/eui.py
easy_user_input-1.2.1.dist-info/LICENSE
easy_user_input-1.2.1.dist-info/WHEEL
easy_user_input-1.2.1.dist-info/METADATA
easy_user_input-1.2.1.dist-info/RECORD
