Metadata-Version: 2.1
Name: easy-user-input
Version: 1.2.1
Summary: Misc python3 methods for collecting input from users
License: MIT
Author: generic-user1
Author-email: 89677116+generic-user1@users.noreply.github.com
Requires-Python: >=3.8,<4.0
Classifier: License :: OSI Approved :: MIT License
Classifier: Programming Language :: Python :: 3
Classifier: Programming Language :: Python :: 3.10
Classifier: Programming Language :: Python :: 3.8
Classifier: Programming Language :: Python :: 3.9
